Metadata-Version: 1.2
Name: cnfcli
Version: 1.0.0
Summary: A CLI tool for command-not-found.com
Home-page: https://github.com/casparwylie/cnfcli
Author: Caspar Wylie
Author-email: casparwylie@gmail.com
License: UNKNOWN
Platform: UNKNOWN
Requires-Python: >=3.8
